Py_Weather.py
Py_Weather-0.0.1.dist-info/LICENSE
Py_Weather-0.0.1.dist-info/METADATA
Py_Weather-0.0.1.dist-info/WHEEL
Py_Weather-0.0.1.dist-info/top_level.txt
Py_Weather-0.0.1.dist-info/RECORD
