Metadata-Version: 2.1
Name: Py-Weather
Version: 0.0.1
Summary: A weather information API
Home-page: UNKNOWN
Author: Kushal Bhavsar
License: UNKNOWN
Keywords: weather,weather info
Platform: UNKNOWN
Classifier: Programming Language :: Python :: 3
Classifier: License :: OSI Approved :: MIT License
Classifier: Operating System :: OS Independent
Requires-Python: >=3.6
Requires-Dist: beautifulsoup4
Requires-Dist: requests
